examples/tracing_on_bert.py
examples/tracing_small_example.py
examples/tracing_with_class_decorator.py
examples/tracing_with_model_instance.py
tests/test_activation_memory_sampler.py
tests/test_gradient_memory_sampler.py
tests/test_layer_memory_sampler.py
tests/test_process_sampler.py
tests/test_pytorch_model_sampler.py
tests/test_system_sampler.py
traceml/__init__.py
traceml/cli.py
traceml/config.py
traceml/decorators.py
traceml/session.py
traceml/tracer.py
traceml/database/__init__.py
traceml/database/database.py
traceml/database/database_writer.py
traceml/loggers/__init__.py
traceml/loggers/error_log.py
traceml/manager/__init__.py
traceml/manager/tracker_manager.py
traceml/renderers/__init__.py
traceml/renderers/activation_gradient_memory_renderer.py
traceml/renderers/base_renderer.py
traceml/renderers/layer_combined_memory_renderer.py
traceml/renderers/layer_combined_timing_renderer.py
traceml/renderers/process_renderer.py
traceml/renderers/stdout_stderr_renderer.py
traceml/renderers/steptimer_renderer.py
traceml/renderers/system_renderer.py
traceml/renderers/utils.py
traceml/renderers/combined_memory/__init__.py
traceml/renderers/combined_memory/services.py
traceml/renderers/combined_timing/__init__.py
traceml/renderers/combined_timing/services.py
traceml/renderers/display/__init__.py
traceml/renderers/display/cli_display_manager.py
traceml/renderers/display/layout.py
traceml/renderers/display/nicegui_display_manager.py
traceml/renderers/display/notebook_display_manager.py
traceml/renderers/display/stdout_stderr_capture.py
traceml/renderers/display/nicegui_sections/helper.py
traceml/renderers/display/nicegui_sections/layer_memory_table_section.py
traceml/renderers/display/nicegui_sections/layer_timer_table_section.py
traceml/renderers/display/nicegui_sections/main_page.py
traceml/renderers/display/nicegui_sections/process_section.py
traceml/renderers/display/nicegui_sections/steptiming_section.py
traceml/renderers/display/nicegui_sections/system_section.py
traceml_ai-0.1.8.dist-info/licenses/LICENSE
traceml_ai-0.1.8.dist-info/METADATA
traceml_ai-0.1.8.dist-info/WHEEL
traceml_ai-0.1.8.dist-info/entry_points.txt
traceml_ai-0.1.8.dist-info/top_level.txt
traceml_ai-0.1.8.dist-info/RECORD
