Metadata-Version: 2.4
Name: traceml-ai
Version: 0.1.8
Summary: TraceML: Lightweight ML Profiler
Author-email: Abhinav Srivastav <abhinavsriva@gmail.com>
License: MIT License
Requires-Python: >=3.9
License-File: LICENSE
Requires-Dist: rich>=12.0.0
Requires-Dist: psutil>=5.0.0
Requires-Dist: torch>=2.5.0
Requires-Dist: pynvml>=11.5.0
Requires-Dist: scikit-learn>=1.3.0
Requires-Dist: numpy<2
Requires-Dist: pandas>=2.0.0
Requires-Dist: pytest>=8.4.1
Requires-Dist: coverage>=7.10.5
Requires-Dist: pytest-cov>=7.0.0
Requires-Dist: ipython>=7.0.0
Requires-Dist: ipywidgets>=7.5.0
Requires-Dist: nicegui
Requires-Dist: plotly
Provides-Extra: dev
Requires-Dist: black>=25.0.0; extra == "dev"
Requires-Dist: flake8>=7.0.0; extra == "dev"
Requires-Dist: pytest>=8.0.0; extra == "dev"
Requires-Dist: datasets; extra == "dev"
Requires-Dist: transformers; extra == "dev"
Dynamic: license-file
